Workbook

Sheet Assumptions
A1: Assumption | B1: 2026E | C1: 2027E | D1: 2028E | E1: 2029E
A2: Revenue Growth | B2: 0.2 | C2: 0.18 | D2: 0.16 | E2: 0.14
A3: EBITDA Margin | B3: 0.31 | C3: 0.32 | D3: 0.33 | E3: 0.34
A4: Tax Rate | B4: 0.25 | C4: 0.25 | D4: 0.25 | E4: 0.25
A5: CapEx % Revenue | B5: 0.05 | C5: 0.05 | D5: 0.05 | E5: 0.05
A6: D&A % Revenue | B6: 0.06 | C6: 0.058 | D6: 0.055 | E6: 0.055
A7: Net Income % Revenue | B7: 0.14 | C7: 0.15 | D7: 0.16 | E7: 0.16
A8: Loan Growth | B8: 0.25 | C8: 0.22 | D8: 0.18 | E8: 0.15
A9: Deposit Growth | B9: 0.3 | C9: 0.25 | D9: 0.2 | E9: 0.18
A10: Provision % Loans | B10: 0.0008 | C10: 0.0008 | D10: 0.0009 | E10: 0.001
A11: WACC | B11: 0.09 | C11: 0.09 | D11: 0.09 | E11: 0.09
A12: Terminal Growth | B12: 0.025 | C12: 0.025 | D12: 0.025 | E12: 0.025

Sheet Historicals
A1: ($ in thousands)
A2: Metric | B2: 2022 | C2: 2023 | D2: 2024 | E2: 2025
A3: Revenue | B3: 1573535 | C3: 2122789 | D3: 2674859 | E3: 3613354
A4: Adjusted EBITDA | B4: 143000 | C4: 432000 | D4: 665000 | E4: 1100000
A5: Net Income | B5: -320407 | C5: -300742 | D5: 498665 | E5: 481320
A6: Depreciation & Amortization | B6: 151360 | C6: 201416 | D6: 203498 | E6: 234151
A7: Capital Expenditures | B7: 93201 | C7: 111409 | D7: 154265 | E7: 242444
A8: Cash | B8: 1421907 | C8: 3085020 | D8: 2538293 | E8: 4929452
A9: Debt | B9: 5485882 | C9: 5233416 | D9: 3092692 | E9: 1815162
A10: Total Loans | B10: =13557074+307957 -> 13865031 | C10: =15396771+6725484+836159 -> 22958414 | D10: =8597368+1246458+17684892 -> 27528718 | E10: =13657578+1516736+22862749 -> 38037063
A11: Customer Deposits | B11: 7342296 | C11: 18620663 | D11: 25978204 | E11: 37505395
A12: Provision for Credit Losses | B12: 54332 | C12: 54945 | D12: 31712 | E12: 30319
A13: Interest Expense | B13: 189275 | C13: 789327 | D13: 1091336 | E13: 1156243
A14: Income Tax Benefit (Expense) | B14: -1686 | C14: 416 | D14: 265320 | E14: -44537
A17: Historical Margins
A18: Metric | B18: 2022 | C18: 2023 | D18: 2024 | E18: 2025
A19: Revenue Growth | B19: NA | C19: =(C3-B3)/B3 -> 0.34905738 | D19: =(D3-C3)/C3 -> 0.26006824 | E19: =(E3-D3)/D3 -> 0.35085775
A20: EBITDA % Revenue | B20: =B4/B3 -> 0.090878182 | C20: =C4/C3 -> 0.20350586 | D20: =D4/D3 -> 0.24861124 | E20: =E4/E3 -> 0.3044263
A21: Net Income % Revenue | B21: =B5/B3 -> -0.20362242 | C21: =C5/C3 -> -0.14167305 | D21: =D5/D3 -> 0.18642665 | E21: =E5/E3 -> 0.13320588
A22: D&A % Revenue | B22: =B6/B3 -> 0.09619106 | C22: =C6/C3 -> 0.094882723 | D22: =D6/D3 -> 0.076078029 | E22: =E6/E3 -> 0.064801567
A23: CapEx % Revenue | B23: =B7/B3 -> 0.059230332 | C23: =C7/C3 -> 0.052482371 | D23: =D7/D3 -> 0.057672199 | E23: =E7/E3 -> 0.067096664
A24: Loan Growth | B24: NA | C24: =(C10-B10)/B10 -> 0.65585017 | D24: =(D10-C10)/C10 -> 0.1990688 | E24: =(E10-D10)/D10 -> 0.38172301
A25: Deposit Growth | B25: NA | C25: =(C11-B11)/B11 -> 1.5360818 | D25: =(D11-C11)/C11 -> 0.39512777 | E25: =(E11-D11)/D11 -> 0.44372548
A26: Provision % Loans | B26: =B12/B10 -> 0.0039186353 | C26: =C12/C10 -> 0.0023932402 | D26: =D12/D10 -> 0.0011519607 | E26: =E12/E10 -> 0.00079709098

Sheet Forecast
A1: ($ in thousands)
A2: ($ in thousands)
A3: Metric | B3: 2025A | C3: 2026E | D3: 2027E | E3: 2028E | F3: 2029E
A4: Revenue | B4: =Historicals!E3 -> 3613354 | C4: =B4*(1+Assumptions!B2) -> 4336024.8 | D4: =C4*(1+Assumptions!C2) -> 5116509.3 | E4: =D4*(1+Assumptions!D2) -> 5935150.7 | F4: =E4*(1+Assumptions!E2) -> 6766071.9
A5: Adjusted EBITDA | B5: =Historicals!E4 -> 1100000 | C5: =C4*Assumptions!B3 -> 1344167.7 | D5: =D4*Assumptions!C3 -> 1637283 | E5: =E4*Assumptions!D3 -> 1958599.7 | F5: =F4*Assumptions!E3 -> 2300464.4
A6: Net Income | B6: =Historicals!E5 -> 481320 | C6: =C4*Assumptions!B7 -> 607043.47 | D6: =D4*Assumptions!C7 -> 767476.39 | E6: =E4*Assumptions!D7 -> 949624.12 | F6: =F4*Assumptions!E7 -> 1082571.5
A7: Capital Expenditures | B7: =Historicals!E7 -> 242444 | C7: =C4*Assumptions!B5 -> 216801.24 | D7: =D4*Assumptions!C5 -> 255825.46 | E7: =E4*Assumptions!D5 -> 296757.54 | F7: =F4*Assumptions!E5 -> 338303.59
A8: Total Loans | B8: =Historicals!E10 -> 38037063 | C8: =B8*(1+Assumptions!B8) -> 47546329 | D8: =C8*(1+Assumptions!C8) -> 58006521 | E8: =D8*(1+Assumptions!D8) -> 68447695 | F8: =E8*(1+Assumptions!E8) -> 78714849
A9: Customer Deposits | B9: =Historicals!E11 -> 37505395 | C9: =B9*(1+Assumptions!B9) -> 48757014 | D9: =C9*(1+Assumptions!C9) -> 60946267 | E9: =D9*(1+Assumptions!D9) -> 73135520 | F9: =E9*(1+Assumptions!E9) -> 86299914
A10: Provision for Credit Losses | B10: =Historicals!E12 -> 30319 | C10: =C8*Assumptions!B10 -> 38037.063 | D10: =D8*Assumptions!C10 -> 46405.217 | E10: =E8*Assumptions!D10 -> 61602.925 | F10: =F8*Assumptions!E10 -> 78714.849
A11: D&A | B11: =Historicals!E6 -> 234151 | C11: =C4*Assumptions!B6 -> 260161.49 | D11: =D4*Assumptions!C6 -> 296757.54 | E11: =E4*Assumptions!D6 -> 326433.29 | F11: =F4*Assumptions!E6 -> 372133.95

Sheet DCF
A1: ($ in thousands)
A2: Metric | B2: 2026E | C2: 2027E | D2: 2028E | E2: 2029E
A3: Revenue | B3: =Forecast!C4 -> 4336024.8 | C3: =Forecast!D4 -> 5116509.3 | D3: =Forecast!E4 -> 5935150.7 | E3: =Forecast!F4 -> 6766071.9
A4: Adjusted EBITDA | B4: =Forecast!C5 -> 1344167.7 | C4: =Forecast!D5 -> 1637283 | D4: =Forecast!E5 -> 1958599.7 | E4: =Forecast!F5 -> 2300464.4
A5: D&A | B5: =Forecast!C11 -> 260161.49 | C5: =Forecast!D11 -> 296757.54 | D5: =Forecast!E11 -> 326433.29 | E5: =Forecast!F11 -> 372133.95
A6: Adjusted EBIT | B6: =B4-B5 -> 1084006.2 | C6: =C4-C5 -> 1340525.4 | D6: =D4-D5 -> 1632166.5 | E6: =E4-E5 -> 1928330.5
A7: Tax Rate | B7: =Assumptions!B4 -> 0.25 | C7: =Assumptions!C4 -> 0.25 | D7: =Assumptions!D4 -> 0.25 | E7: =Assumptions!E4 -> 0.25
A8: NOPAT | B8: =B6*(1-B7) -> 813004.65 | C8: =C6*(1-C7) -> 1005394.1 | D8: =D6*(1-D7) -> 1224124.8 | E8: =E6*(1-E7) -> 1446247.9
A9: Add: D&A | B9: =B5 -> 260161.49 | C9: =C5 -> 296757.54 | D9: =D5 -> 326433.29 | E9: =E5 -> 372133.95
A10: Less: CapEx | B10: =Forecast!C7 -> 216801.24 | C10: =Forecast!D7 -> 255825.46 | D10: =Forecast!E7 -> 296757.54 | E10: =Forecast!F7 -> 338303.59
A11: Free Cash Flow | B11: =B8+B9-B10 -> 856364.9 | C11: =C8+C9-C10 -> 1046326.1 | D11: =D8+D9-D10 -> 1253800.6 | E11: =E8+E9-E10 -> 1480078.2
A12: PV of FCF | B12: =B11/(1+B15)^1 -> 785655.87 | C12: =C11/(1+B15)^2 -> 880671.78 | D12: =D11/(1+B15)^3 -> 968164.11 | E12: =E11/(1+B15)^4 -> 1048524.7
A14: Metric | B14: Value
A15: WACC | B15: 0.09
A16: Terminal Growth | B16: 0.025
A17: PV of FCF's | B17: =SUM(B12:E12) -> 3683016.5
A18: PV of Terminal Value | B18: =B31/(1+B15)^4 -> 16534428
A19: Enterprise Value | B19: =B17+B18 -> 20217445
A20: Add: Cash | B20: =Historicals!E8 -> 4929452
A21: Less: Debt | B21: =Historicals!E9 -> 1815162
A22: Equity Value | B22: =B19+B20-B21 -> 23331735
A23: Shares Outstanding | B23: 1250000
A24: Implied Share Price | B24: =B22/B23 -> 18.665388
A25: Current Stock Price (05/06/2026) | B25: 16.3
A26: Upside (Downside) | B26: =(B24-B25)/B25 -> 0.14511582
A27: Recommendation | B27: Moderate Buy
A29: Terminal Value Calculations | B29: Value
A30: 2030 FCF | B30: =E11*(1+B16) -> 1517080.2
A31: Terminal Vaue | B31: =B30/(B15-B16) -> 23339695
A34: DCF Sensitivity Analysis | B34: Implied Share Price ($ per share)
D36: Terminal Growth
B37: =B24 -> 18.665388 | C37: 0.015 | D37: 0.02 | E37: 0.025 | F37: 0.03 | G37: 0.035
B38: 0.075 | C38: 20.545866 | D38: 21.989992 | E38: 23.722945 | F38: 25.840997 | G38: 28.488563
B39: 0.08 | C39: 19.100391 | D39: 20.305451 | E39: 21.729613 | F39: 23.438608 | G39: 25.527379
B40: 0.085 | C40: 17.862219 | D40: 18.880913 | E40: 20.06939 | F40: 21.473954 | G40: 23.159431
A41: WACC | B41: 0.09 | C41: 16.789873 | D41: 17.660648 | E41: 18.665388 | F41: 19.837585 | G41: 21.222908
B42: 0.095 | C42: 15.852247 | D42: 16.603785 | E42: 17.462686 | F42: 18.453725 | G42: 19.609938
B43: 0.1 | C43: 15.025554 | D43: 15.679675 | E43: 16.421011 | F43: 17.268253 | G43: 18.245839
B44: 0.105 | C44: 14.291293 | D44: 14.864877 | E44: 15.510158 | F44: 16.241476 | G44: 17.077269

Sheet Recommendation
A1: SOFI Technologies Valuation Summary
A3: Metric | C3: Value
A4: Recommendation | C4: Buy
A5: Implied Share Price | C5: 18.67
A6: Current Share Price | C6: 16.3
A7: Upside Potential | C7: 0.1451
A8: WACC | C8: 0.09
A9: Terminal Growth Rate | C9: 0.025
A12: INVESTMENT THESIS
A14: • Strong projected revenue growth driven by continued expansion in lending, deposits, and consumer financial products.
A15: • Rapid customer deposit growth improves funding and helps long-term loan growth
A16: • Improving margins and profitability may support further upside in the company's valuation
A19: KEY FORECAST DRIVERS
A21: Key Driver | B21: 2026E | C21: 2027E | D21: 2028E | E21: 2029E
A22: Revenue Growth | B22: 0.2 | C22: 0.18 | D22: 0.16 | E22: 0.14
A23: Adjusted EBITDA Margin | B23: 0.31 | C23: 0.32 | D23: 0.33 | E23: 0.34
A24: Loan Growth | B24: 0.25 | C24: 0.22 | D24: 0.18 | E24: 0.15
A25: Deposit Growth | B25: 0.3 | C25: 0.25 | D25: 0.2 | E25: 0.18
A28: VALUATION COMMENTARY
A30: Using a discounted cash flow valuation with a 9.0% WACC and 2.5% terminal growth rate,
A31: the model estimates an implied share price of $18.67, representing approximately 14.5%
A32: upside from the current market price of $16.30.
A34: This valuation is supported by by projected growth in revenue, deposits, and profitability
A35: over the forecast period.
A38: RISKS SECTION
A40: Key Risks
A41: • Increased credit losses may reduce future earnings and margins.
A42: • Slower loan or deposit growth could reduce projected revenue expansion.
A43: • Macroeconomic weakness or interest rate fluctuations may negatvely affect consumer lending activity.
A44: • Regulatory changes may impact future growth and profitability.
... A69: credit performance and macroeconomic conditions.
